voltools/__init__.py
voltools/transforms.py
voltools/volume.py
voltools/kernels/bspline.h
voltools/kernels/helper_interpolation.h
voltools/kernels/helper_math.h
voltools/utils/__init__.py
voltools/utils/general.py
voltools/utils/matrices.py
voltools-0.6.0.dist-info/LICENSE.md
voltools-0.6.0.dist-info/METADATA
voltools-0.6.0.dist-info/WHEEL
voltools-0.6.0.dist-info/top_level.txt
voltools-0.6.0.dist-info/RECORD
