Metadata-Version: 2.1
Name: voltools
Version: 0.6.0
Summary: CUDA-accelerated 3D affine transformations for NumPy and CuPy
Home-page: https://github.com/the-lay/voltools
Author: the-lay
Author-email: ilja.gubin@gmail.com
License: MIT
Platform: any
Classifier: Development Status :: 3 - Alpha
Classifier: Intended Audience :: Developers
Classifier: Intended Audience :: Science/Research
Classifier: Topic :: Software Development :: Libraries :: Python Modules
Classifier: License :: OSI Approved :: MIT License
Classifier: Programming Language :: Python :: 3 :: Only
License-File: LICENSE.md
